compositions/__init__.py
compositions/__main__.py
compositions/compositions.py
Compositions-1.0.2.1.dist-info/LICENSE
Compositions-1.0.2.1.dist-info/METADATA
Compositions-1.0.2.1.dist-info/WHEEL
Compositions-1.0.2.1.dist-info/entry_points.txt
Compositions-1.0.2.1.dist-info/top_level.txt
Compositions-1.0.2.1.dist-info/RECORD
