Metadata-Version: 2.1
Name: Compositions
Version: 1.0.2.1
Summary: Contains composition of useful structures
Home-page: https://ComposedStructures.github.io
Author: QuantumNovice
Author-email: portabl3lapy@gmail.com
License: MIT
Platform: UNKNOWN
Classifier: License :: OSI Approved :: MIT License
Classifier: Programming Language :: Python :: 3
Classifier: Programming Language :: Python :: 3.7
Requires-Python: >=3.6
